vqueue/__init__.py
vqueue/_config.py
vqueue/config.toml
vqueue/exceptions.py
vqueue/py.typed
vqueue/queues.py
vqueue/types.py
vqueue/utils.py
vqueue_sdk-0.1.2.dist-info/METADATA
vqueue_sdk-0.1.2.dist-info/WHEEL
vqueue_sdk-0.1.2.dist-info/top_level.txt
vqueue_sdk-0.1.2.dist-info/RECORD
