Metadata-Version: 2.4
Name: vqueue-sdk
Version: 0.1.2
Summary: A toolset for Virtual Queue integrations in Python
Author-email: "Animus Coop." <info@animus.com.ar>
License-Expression: MIT
Project-URL: Homepage, https://github.com/animus-coop/virtual-queue-python-sdk
Keywords: tickets,queue,async,events,high-demand
Classifier: Programming Language :: Python :: 3
Requires-Python: >=3.10
Requires-Dist: requests
Requires-Dist: tomli; python_version < "3.11"
